{
  "flags": {
    "foundry-ironsworn": {
      "dfid": "Ironsworn/Oracles/Moves/Delve_the_Depths/Shadow",
      "category": "Ironsworn/Moves/Delve",
      "dsid": "move.oracle_rollable:delve/delve/delve_the_depths.shadow"
    }
  },
  "name": "Shadow",
  "description": "",
  "formula": "1d100",
  "replacement": true,
  "displayRoll": true,
  "results": [
    {
      "range": [
        1,
        30
      ],
      "_id": "28f7779e589dc657",
      "type": "text",
      "img": null,
      "weight": 1,
      "drawn": false,
      "flags": {},
      "_stats": {
        "coreVersion": "13.350",
        "systemId": null,
        "systemVersion": null,
        "createdTime": null,
        "modifiedTime": null,
        "lastModifiedBy": null,
        "compendiumSource": null,
        "duplicateSource": null,
        "exportSource": null
      },
      "description": "Mark progress and @Compendium[foundry-ironsworn.ironsworndelvemoves.06f78b87b9532437]{Reveal a Danger}.",
      "name": "",
      "_key": "!tables.results!0PL7DWClXfmxhCKI.28f7779e589dc657"
    },
    {
      "range": [
        31,
        65
      ],
      "_id": "c63b09d259d98c9f",
      "type": "text",
      "img": null,
      "weight": 1,
      "drawn": false,
      "flags": {},
      "_stats": {
        "coreVersion": "13.350",
        "systemId": null,
        "systemVersion": null,
        "createdTime": null,
        "modifiedTime": null,
        "lastModifiedBy": null,
        "compendiumSource": null,
        "duplicateSource": null,
        "exportSource": null
      },
      "description": "Mark progress.",
      "name": "",
      "_key": "!tables.results!0PL7DWClXfmxhCKI.c63b09d259d98c9f"
    },
    {
      "range": [
        66,
        90
      ],
      "_id": "084a86b3e0c9604a",
      "type": "text",
      "img": null,
      "weight": 1,
      "drawn": false,
      "flags": {},
      "_stats": {
        "coreVersion": "13.350",
        "systemId": null,
        "systemVersion": null,
        "createdTime": null,
        "modifiedTime": null,
        "lastModifiedBy": null,
        "compendiumSource": null,
        "duplicateSource": null,
        "exportSource": null
      },
      "description": "Choose one: Mark progress or @Compendium[foundry-ironsworn.ironsworndelvemoves.4da87fd54eaa1b89]{Find an Opportunity}.",
      "name": "",
      "_key": "!tables.results!0PL7DWClXfmxhCKI.084a86b3e0c9604a"
    },
    {
      "range": [
        91,
        99
      ],
      "_id": "07ba1f885c84036d",
      "type": "text",
      "img": null,
      "weight": 1,
      "drawn": false,
      "flags": {},
      "_stats": {
        "coreVersion": "13.350",
        "systemId": null,
        "systemVersion": null,
        "createdTime": null,
        "modifiedTime": null,
        "lastModifiedBy": null,
        "compendiumSource": null,
        "duplicateSource": null,
        "exportSource": null
      },
      "description": "Take both: Mark progress and @Compendium[foundry-ironsworn.ironsworndelvemoves.4da87fd54eaa1b89]{Find an Opportunity}.",
      "name": "",
      "_key": "!tables.results!0PL7DWClXfmxhCKI.07ba1f885c84036d"
    },
    {
      "range": [
        100,
        100
      ],
      "_id": "4c13e2e02c90b279",
      "type": "text",
      "img": null,
      "weight": 1,
      "drawn": false,
      "flags": {},
      "_stats": {
        "coreVersion": "13.350",
        "systemId": null,
        "systemVersion": null,
        "createdTime": null,
        "modifiedTime": null,
        "lastModifiedBy": null,
        "compendiumSource": null,
        "duplicateSource": null,
        "exportSource": null
      },
      "description": "Mark progress twice and @Compendium[foundry-ironsworn.ironsworndelvemoves.06f78b87b9532437]{Reveal a Danger}.",
      "name": "",
      "_key": "!tables.results!0PL7DWClXfmxhCKI.4c13e2e02c90b279"
    }
  ],
  "folder": "Et6gYyWzqZwieobL",
  "img": "icons/dice/d10black.svg",
  "_stats": {
    "compendiumSource": null,
    "duplicateSource": null,
    "coreVersion": "13.350",
    "systemId": "foundry-ironsworn",
    "systemVersion": "1.25.4",
    "createdTime": 1758484144927,
    "modifiedTime": 1758484144927,
    "lastModifiedBy": "MmM06BuCrG9h1GLg",
    "exportSource": null
  },
  "ownership": {
    "default": 0,
    "MmM06BuCrG9h1GLg": 3
  },
  "_id": "0PL7DWClXfmxhCKI",
  "sort": 0,
  "_key": "!tables!0PL7DWClXfmxhCKI"
}
